lean_server/__init__.py
lean_server/app/__init__.py
lean_server/app/args.py
lean_server/app/lifespan.py
lean_server/app/prove.py
lean_server/app/serve.py
lean_server/config/__init__.py
lean_server/config/config.py
lean_server/database/__init__.py
lean_server/database/proof.py
lean_server/manager/__init__.py
lean_server/manager/proof_manager.py
lean_server/proof/__init__.py
lean_server/proof/lean.py
lean_server/proof/proto.py
lean_server/utils/uuid/uuid.py
lmms_lean_server-0.0.1.dev4.dist-info/licenses/LICENSE
lmms_lean_server-0.0.1.dev4.dist-info/METADATA
lmms_lean_server-0.0.1.dev4.dist-info/WHEEL
lmms_lean_server-0.0.1.dev4.dist-info/entry_points.txt
lmms_lean_server-0.0.1.dev4.dist-info/top_level.txt
lmms_lean_server-0.0.1.dev4.dist-info/RECORD
