Metadata-Version: 2.4
Name: lmms-lean-server
Version: 0.0.1.dev4
Summary: A FastAPI-based server to interact with the Lean Theorem Prover.
Author-email: Pu Fanyi <FPU001@e.ntu.edu.sg>
License: MIT
Project-URL: Repository, https://github.com/pufanyi/lean-server
Project-URL: Homepage, https://github.com/pufanyi/lean-server
Keywords: lean,lean-server,theorem prover,fastapi
Classifier: Programming Language :: Python :: 3
Classifier: License :: OSI Approved :: MIT License
Classifier: Operating System :: OS Independent
Classifier: Framework :: FastAPI
Requires-Python: >=3.12
License-File: LICENSE
Requires-Dist: pydantic>=2.11.7
Requires-Dist: pyyaml>=6.0.2
Requires-Dist: loguru>=0.7.2
Requires-Dist: fastapi>=0.116.1
Requires-Dist: uvicorn>=0.35.0
Requires-Dist: rich>=14.1.0
Requires-Dist: aiosqlite>=0.21.0
Requires-Dist: python-multipart>=0.0.20
Requires-Dist: aiohttp>=3.12.15
Requires-Dist: uuid-utils>=0.11.0
Requires-Dist: datasets>=4.0.0
Dynamic: license-file
